[
    {
        "key": "dbln",
        "value": "%7B%22100077754499962%22%3A%22unlQ28Zc%22%7D",
        "domain": "facebook.com",
        "path": "/login/device-based/",
        "hostOnly": false,
        "creation": "2025-08-16T20:10:09.323Z",
        "lastAccessed": "2025-08-16T20:10:09.324Z"
    },
    {
        "key": "datr",
        "value": "uPWYaKHuPxbTuicc7mp52qmz",
        "domain": "facebook.com",
        "path": "/",
        "hostOnly": false,
        "creation": "2025-08-16T20:10:09.324Z",
        "lastAccessed": "2025-08-16T20:10:09.324Z"
    },
    {
        "key": "sb",
        "value": "ufWYaKjV2INqLzXPgotgOSno",
        "domain": "facebook.com",
        "path": "/",
        "hostOnly": false,
        "creation": "2025-08-16T20:10:09.324Z",
        "lastAccessed": "2025-08-16T20:10:09.324Z"
    },
    {
        "key": "locale",
        "value": "bn_IN",
        "domain": "facebook.com",
        "path": "/",
        "hostOnly": false,
        "creation": "2025-08-16T20:10:09.324Z",
        "lastAccessed": "2025-08-16T20:10:09.324Z"
    },
    {
        "key": "pas",
        "value": "100077754499962%3AK3W521E5PA",
        "domain": "facebook.com",
        "path": "/",
        "hostOnly": false,
        "creation": "2025-08-16T20:10:09.324Z",
        "lastAccessed": "2025-08-16T20:10:09.324Z"
    },
    {
        "key": "vpd",
        "value": "v1%3B665x360x3",
        "domain": "facebook.com",
        "path": "/",
        "hostOnly": false,
        "creation": "2025-08-16T20:10:09.324Z",
        "lastAccessed": "2025-08-16T20:10:09.324Z"
    },
    {
        "key": "wl_cbv",
        "value": "v2%3Bclient_version%3A2894%3Btimestamp%3A1755363334",
        "domain": "facebook.com",
        "path": "/",
        "hostOnly": false,
        "creation": "2025-08-16T20:10:09.324Z",
        "lastAccessed": "2025-08-16T20:10:09.324Z"
    },
    {
        "key": "fr",
        "value": "04VstdoRpwGzZSYc2.AWd61dTaltSdqhESxaZZJLmV1-2FDIiJvKPmPk00fMCaIT-nBRY.BomPW5..AAA.0.0.BooOVR.AWdZ_kdO-joKnuLEfPnxB119OvU",
        "domain": "facebook.com",
        "path": "/",
        "hostOnly": false,
        "creation": "2025-08-16T20:10:09.324Z",
        "lastAccessed": "2025-08-16T20:10:09.324Z"
    }
        ]
